core/__init__.py
core/types.py
dashboard/__init__.py
dashboard/server.py
dashboard/static/css/dashboard.css
dashboard/static/images/favicon.ico
dashboard/static/js/dashboard.js
dashboard/templates/base.html
dashboard/templates/dashboard.html
inspector/README.md
inspector/__init__.py
inspector/main.py
inspector/checks/__init__.py
inspector/checks/accessibility_scanner.py
inspector/checks/base_scanner.py
inspector/checks/performance_scanner.py
inspector/checks/structured_explorer.py
inspector/playwright_helpers/__init__.py
inspector/playwright_helpers/link_detection.py
inspector/playwright_helpers/page_setup.py
inspector/utils/__init__.py
inspector/utils/action_recorder.py
inspector/utils/analyzer_factory.py
inspector/utils/bug_deduplicator.py
inspector/utils/cohere_analyzer.py
inspector/utils/evidence.py
inspector/utils/gemini_analyzer.py
inspector/utils/interaction_tracker.py
inspector/utils/performance.py
inspector/utils/scroll_manager.py
mantis_web_crawler-1.4.1.dist-info/licenses/LICENSE
orchestrator/__init__.py
orchestrator/cli.py
orchestrator/crawler.py
orchestrator/url_utils.py
tests/__init__.py
tests/conftest.py
tests/minimal_test.py
tests/test_inspector.py
mantis_web_crawler-1.4.1.dist-info/METADATA
mantis_web_crawler-1.4.1.dist-info/WHEEL
mantis_web_crawler-1.4.1.dist-info/entry_points.txt
mantis_web_crawler-1.4.1.dist-info/top_level.txt
mantis_web_crawler-1.4.1.dist-info/RECORD
