Metadata-Version: 2.4
Name: mantis-web-crawler
Version: 1.4.1
Summary: Web accessibility and UI bug detection tool
Home-page: https://github.com/yourusername/mantis
Author: Mantis Team
Author-email: 
License: MIT
Project-URL: Homepage, https://github.com/yourusername/mantis
Project-URL: Repository, https://github.com/yourusername/mantis
Project-URL: Bug Reports, https://github.com/yourusername/mantis/issues
Keywords: web-crawler,accessibility,ui-testing,bug-detection,playwright
Classifier: Development Status :: 4 - Beta
Classifier: Intended Audience :: Developers
Classifier: License :: OSI Approved :: MIT License
Classifier: Operating System :: OS Independent
Classifier: Programming Language :: Python :: 3
Classifier: Programming Language :: Python :: 3.8
Classifier: Programming Language :: Python :: 3.9
Classifier: Programming Language :: Python :: 3.10
Classifier: Programming Language :: Python :: 3.11
Classifier: Programming Language :: Python :: 3.12
Classifier: Topic :: Internet :: WWW/HTTP
Classifier: Topic :: Software Development :: Testing
Classifier: Topic :: Software Development :: Quality Assurance
Requires-Python: >=3.8
License-File: LICENSE
Requires-Dist: playwright>=1.40.0
Requires-Dist: flask>=2.0.0
Requires-Dist: flask-socketio>=5.0.0
Requires-Dist: beautifulsoup4>=4.9.0
Requires-Dist: aiohttp>=3.8.0
Requires-Dist: asyncio-mqtt>=0.11.0
Requires-Dist: requests>=2.25.0
Requires-Dist: lxml>=4.6.0
Requires-Dist: python-socketio[client]>=5.0.0
Requires-Dist: cohere>=5.11.0
Requires-Dist: python-dotenv>=1.0.0
Requires-Dist: axe-playwright-python>=0.1.0
Provides-Extra: dev
Requires-Dist: pytest>=6.0; extra == "dev"
Requires-Dist: pytest-asyncio>=0.18.0; extra == "dev"
Requires-Dist: black>=21.0.0; extra == "dev"
Requires-Dist: flake8>=3.9.0; extra == "dev"
Requires-Dist: mypy>=0.910; extra == "dev"
Dynamic: home-page
Dynamic: license-file
Dynamic: requires-python
